socianAuthPyTest/__init__.py
socianAuthPyTest-0.1.8.dist-info/LICENSE.txt
socianAuthPyTest-0.1.8.dist-info/METADATA
socianAuthPyTest-0.1.8.dist-info/WHEEL
socianAuthPyTest-0.1.8.dist-info/top_level.txt
socianAuthPyTest-0.1.8.dist-info/RECORD
